Metadata-Version: 2.1
Name: botways-pypi-helloworld-test
Version: 1.0.0
Summary: First Test
Home-page: UNKNOWN
Author: <authorname>
Author-email: <authorname@templatepackage.com>
License: UNKNOWN
Platform: UNKNOWN
Classifier: Programming Language :: Python :: 3
Classifier: Operating System :: OS Independent
Classifier: Operating System :: Microsoft :: Windows
Requires-Python: >=3.6
